stockdatareader/__init__.py
stockdatareader/stockdatareader.py
stockdatareader/utils.py
stockdatareader-1.0.0.dist-info/AUTHORS
stockdatareader-1.0.0.dist-info/LICENSE
stockdatareader-1.0.0.dist-info/METADATA
stockdatareader-1.0.0.dist-info/WHEEL
stockdatareader-1.0.0.dist-info/pbr.json
stockdatareader-1.0.0.dist-info/top_level.txt
stockdatareader-1.0.0.dist-info/RECORD
