Metadata-Version: 2.1
Name: stockdatareader
Version: 1.0.0
Summary: Read online stock data
Home-page: https://github.com/kricki/stockdatareader
Author: kricki
License: UNKNOWN
Platform: UNKNOWN
Classifier: Development Status :: 5 - Production/Stable
Classifier: Intended Audience :: Financial and Insurance Industry
Classifier: Intended Audience :: Developers
Classifier: Programming Language :: Python :: 3.7
Classifier: Topic :: Office/Business :: Financial
Requires-Dist: pandas
Requires-Dist: mechanicalsoup
Requires-Dist: python-stdnum
Requires-Dist: html5lib
